{
    "pid": "delphinium aurora f1 deep purple",
    "basic": {
        "floral_language": "Delphinium x 'Black Knight'\nFloriography: elegant, plain, beautiful.\nThe plant is an annual flowering herbaceous. It is very popular because of its plant profile, unique flower shape and various flower colors. Garden uses include flower beds, edges and family pots.\nThis plant likes sunny habitat. It is partial shade tolerant during growth but requires sunlight during flowering. It blooms in June to September for two to three weeks.",
        "origin": "Europe",
        "production": "China",
        "category": "Scrophulariaceae, Penstemon",
        "blooming": "Flowering period June-September, viewing period 2-3 weeks",
        "color": "Flower color deep purple"
    },
    "display_pid": "Delphinium Aurora F1 Deep Purple",
    "maintenance": {
        "size": "Diameter \u2265 10 cm, height \u2265 15 cm",
        "soil": "Peat or soil with specific nutrients",
        "sunlight": "Likes light, half shade when growing, need adequate sunshine when flowering",
        "watering": "Water thoroughly after soil surface dries",
        "fertilization": "Dilute fertilizers following instructions,  apply 1-2 times monthly in spring",
        "pruning": "Remove withered flowers, old, diseased, and dead leaves timely"
    },
    "parameter": {
        "max_light_mmol": 5000,
        "min_light_mmol": 3500,
        "max_light_lux": 50000,
        "min_light_lux": 3000,
        "max_temp": 35,
        "min_temp": 5,
        "max_env_humid": 80,
        "min_env_humid": 30,
        "max_soil_moist": 60,
        "min_soil_moist": 15,
        "max_soil_ec": 2000,
        "min_soil_ec": 350
    },
    "image": "assets/images-sample/delphinium aurora f1 deep purple.jpg"
}