{
    "pid": "elettaria cardamomum",
    "basic": {
        "floral_language": "",
        "origin": "Southern India",
        "production": "Southern China",
        "category": "Zingiberaceae, Elettaria",
        "blooming": "Flowering period June-September",
        "color": "Flower color white"
    },
    "display_pid": "Elettaria cardamomum",
    "maintenance": {
        "size": "Diameter \u2265 20 cm, height 15-20 cm",
        "soil": "Peat or soil with specific nutrients",
        "sunlight": "Like shade environments",
        "watering": "Keep soil moist",
        "fertilization": "Apply enough base fertilizers",
        "pruning": "Remove old, diseased and dead leaves timely"
    },
    "parameter": {
        "max_light_mmol": 2500,
        "min_light_mmol": 1200,
        "max_light_lux": 6000,
        "min_light_lux": 1500,
        "max_temp": 32,
        "min_temp": 8,
        "max_env_humid": 80,
        "min_env_humid": 30,
        "max_soil_moist": 60,
        "min_soil_moist": 15,
        "max_soil_ec": 2000,
        "min_soil_ec": 350
    },
    "image": "assets/images-sample/elettaria cardamomum.jpg"
}