{
    "pid": "ficus aurea",
    "basic": {
        "floral_language": "",
        "origin": "Mediterranean coastal areas",
        "production": "China",
        "category": "Moraceae, Ficus",
        "blooming": "Flowering and fruiting period May-July",
        "color": "Flower very small, green, fruit color purple red or yellow"
    },
    "display_pid": "Ficus aurea",
    "maintenance": {
        "size": "Diameter \u2265 30 cm, height \u2265 40 cm",
        "soil": "Sandy or clay soil with loose texture or soil with specific nutrients",
        "sunlight": "Likes light, better fruit in sunny places",
        "watering": "Resistant to drought, water thoroughly after soil surface dries, avoid saturated water",
        "fertilization": "Dilute fertilizers following instructions, apply 1-2 times monthly",
        "pruning": "Remove aged tissues, dead and pest branches timely"
    },
    "parameter": {
        "max_light_mmol": 6400,
        "min_light_mmol": 4000,
        "max_light_lux": 60000,
        "min_light_lux": 3500,
        "max_temp": 35,
        "min_temp": 5,
        "max_env_humid": 80,
        "min_env_humid": 30,
        "max_soil_moist": 60,
        "min_soil_moist": 15,
        "max_soil_ec": 2000,
        "min_soil_ec": 350
    },
    "image": "assets/images-sample/ficus aurea.jpg"
}