{
    "pid": "myosotis sylvatica",
    "basic": {
        "floral_language": "Myosotis sylvatica \nFloriography: sincerity, loyalty, warmth \nMyosotis sylvatica forms a beautiful blue flower, like a small curved umbrella. Flowers are small delicate, blooming just as its name implies, can continue for a long time, enough to be remembered in deep heart. Moreover, Myosotis sylvatica flowers do not fall after dying, can be made chic dried flower. \nMyosotis sylvatica like sunshine, blooming from May to July, ornamental period lasts three to four weeks",
        "origin": "Holland",
        "production": "Yunnan",
        "category": "Boraginaceae, Myosotis",
        "blooming": "Flowering period May-July, viewing period 3-4 weeks",
        "color": "Flower color blue, purple, white, yellow"
    },
    "display_pid": "Myosotis sylvatica",
    "maintenance": {
        "size": "Diameter \u2265 10 cm, height 15-18 cm",
        "soil": "Likes slightly alkaline soil, may use peat adding a small amount of lime or baking soda,",
        "sunlight": "Likes sunshine, but avoid very strong sunlight",
        "watering": "Moderately resistant to drought, water thoroughly when soil is dry",
        "fertilization": "Dilute fertilizers following instructions, apply 1-2 times monthly",
        "pruning": "Remove old, diseased and dead leaves timely"
    },
    "parameter": {
        "max_light_mmol": 6000,
        "min_light_mmol": 4000,
        "max_light_lux": 60000,
        "min_light_lux": 2200,
        "max_temp": 32,
        "min_temp": 8,
        "max_env_humid": 80,
        "min_env_humid": 30,
        "max_soil_moist": 60,
        "min_soil_moist": 15,
        "max_soil_ec": 2000,
        "min_soil_ec": 350
    },
    "image": "assets/images-sample/myosotis sylvatica.jpg"
}