{
    "pid": "phormium tenax",
    "basic": {
        "floral_language": "",
        "origin": "New Zealand",
        "production": "China",
        "category": "Agavaceae, Phormium",
        "blooming": "Flowering period April-June",
        "color": "Flower color red, green"
    },
    "display_pid": "Phormium tenax",
    "maintenance": {
        "size": "height \u2265 40 cm",
        "soil": "Deep humus-rich sandy loam",
        "sunlight": "Like sunshine, resistant to half shade",
        "watering": "Water thoroughly when soil is dry, avoid saturated water",
        "fertilization": "Dilute fertilizers following instructions, apply 1-2 times monthly",
        "pruning": "Remove aged tissues, dead and pest branches timely"
    },
    "parameter": {
        "max_light_mmol": 4500,
        "min_light_mmol": 2500,
        "max_light_lux": 30000,
        "min_light_lux": 3700,
        "max_temp": 32,
        "min_temp": 8,
        "max_env_humid": 80,
        "min_env_humid": 30,
        "max_soil_moist": 60,
        "min_soil_moist": 15,
        "max_soil_ec": 2000,
        "min_soil_ec": 350
    },
    "image": "assets/images-sample/phormium tenax.jpg"
}