{
    "pid": "red fittonia verschaffeltii",
    "basic": {
        "floral_language": "Red Fittonia verschaffeltii\nFloriography: delicate, refreshing, vitality.\nA small evergreen plant, leaves of the nerve plant are oval with white or red veins intercrossing like a web. Widely used indoor and micro-landscape for decoration.\nThe plant requires partial shade habitat. Two to three hours sunbath in winter is acceptable. Yellow flowers may bloom in September to November if growing well.",
        "origin": "China",
        "production": "China",
        "category": "Acanthaceae, Fittonia",
        "blooming": "Foliage plants, sometimes flowers in September-November, yellow flowers",
        "color": "Leaf red"
    },
    "display_pid": "Red Fittonia verschaffeltii",
    "maintenance": {
        "size": "Diameter \u2265 10 cm, height \u2265 5 cm",
        "soil": "Peat or soil with specific nutrients",
        "sunlight": "Like shade environments, in winter may take 2-3h sunlight",
        "watering": "Need a lot of water, water thoroughly when soil is dry",
        "fertilization": "Dilute fertilizers following instructions, apply 1-2 times monthly in spring and autumn",
        "pruning": "Remove dead leaves timely"
    },
    "parameter": {
        "max_light_mmol": 3300,
        "min_light_mmol": 1200,
        "max_light_lux": 26000,
        "min_light_lux": 500,
        "max_temp": 35,
        "min_temp": 10,
        "max_env_humid": 85,
        "min_env_humid": 30,
        "max_soil_moist": 60,
        "min_soil_moist": 15,
        "max_soil_ec": 2000,
        "min_soil_ec": 350
    },
    "image": "assets/images-sample/red fittonia verschaffeltii.jpg"
}